ireland_nta_mcp-0.0.1.dist-info/licenses/LICENSE
mcp_server_nta/__init__.py
mcp_server_nta/__main__.py
mcp_server_nta/py.typed
mcp_server_nta/server.py
mcp_server_nta/test/__init__.py
mcp_server_nta/test/conftest.py
mcp_server_nta/test/test_enum.py
mcp_server_nta/test/test_init.py
mcp_server_nta/test/test_server.py
ireland_nta_mcp-0.0.1.dist-info/METADATA
ireland_nta_mcp-0.0.1.dist-info/WHEEL
ireland_nta_mcp-0.0.1.dist-info/top_level.txt
ireland_nta_mcp-0.0.1.dist-info/RECORD
