Metadata-Version: 2.4
Name: ireland-nta-mcp
Version: 0.0.1
Summary: A Model Context Protocol server that interfaces with Ireland's NTA API
Requires-Python: >=3.10
License-File: LICENSE
Requires-Dist: gtfs-realtime-bindings>=1.0.0
Requires-Dist: mcp[cli]>=1.12.4
Requires-Dist: protobuf>=6.31.1
Requires-Dist: tzlocal>=5.3.1
Requires-Dist: python-dotenv>=1.0.0
Requires-Dist: httpx>=0.24.0
Provides-Extra: dev
Requires-Dist: pytest>=7.0.0; extra == "dev"
Requires-Dist: pytest-asyncio>=0.21.0; extra == "dev"
Requires-Dist: pytest-mock>=3.10.0; extra == "dev"
Dynamic: license-file
